her/Speecher.py
her/__init__.py
her/db.py
herai-1.0.1.dist-info/METADATA
herai-1.0.1.dist-info/RECORD
herai-1.0.1.dist-info/WHEEL
herai-1.0.1.dist-info/entry_points.txt
herai-1.0.1.dist-info/top_level.txt
